kraken/__init__.py
kraken/analysis/__init__.py
kraken/analysis/data_manipulation.py
kraken/classes/data_types.py
kraken/classes/pack_lists.py
kraken/classes/packs.py
kraken/connection/__init__.py
kraken/connection/connector.py
kraken/connection/support.py
kraken/credentials/__init__.py
kraken/credentials/credential_manager.py
kraken/credentials/credentials.py
kraken/credentials/helpers.py
kraken/credentials/integrity.py
kraken/credentials/save_connection.py
kraken/credentials/save_convenience.py
kraken/exceptions.py
kraken/exporting/__init__.py
kraken/exporting/result_export.py
kraken/exporting/result_export_extensions.py
kraken/graphing/__init__.py
kraken/graphing/graphing.py
kraken/graphing/graphing_graphs.py
kraken/graphing/graphing_support.py
kraken/graphing/graphing_support_lists.py
kraken/importing/__init__.py
kraken/importing/data_import.py
kraken/parsing/__init__.py
kraken/parsing/parsing.py
kraken/parsing/scanning.py
kraken/parsing/support_classes.py
kraken/platforms/__init__.py
kraken/platforms/config.py
kraken/platforms/integrity.py
kraken/platforms/oracle/__init__.py
kraken/ribosome/__init__.py
kraken/ribosome/ribosome.py
kraken/ribosome/sql_execution.py
kraken/ribosome/sql_extraction.py
kraken/ribosome/support.py
kraken/support/__init__.py
kraken/support/progress.py
kraken/support/readout.py
kraken/support/support.py
kraken/support/support_checks.py
kraken/support/support_classes.py
kraken/support/warnings.py
kraken/uploading/__init__.py
kraken/uploading/data_upload.py
kraken/uploading/support.py
kraken/uploading/uploader.py
datakraken-1.1.8.dist-info/LICENSE
datakraken-1.1.8.dist-info/METADATA
datakraken-1.1.8.dist-info/WHEEL
datakraken-1.1.8.dist-info/RECORD
