Metadata-Version: 2.3
Name: datakraken
Version: 1.1.8
Summary: Kraken is a convenience package that orchestrates data extraction by integrating SQL with Python, while managing safe storage and recall of sensitive connection credentials.
License: CC BY-NC 4.0
Author: Cai Davis
Requires-Python: >=3.10,<4.0
Classifier: License :: Other/Proprietary License
Classifier: Programming Language :: Python :: 3
Classifier: Programming Language :: Python :: 3.10
Classifier: Programming Language :: Python :: 3.11
Classifier: Programming Language :: Python :: 3.12
Classifier: Programming Language :: Python :: 3.13
Requires-Dist: charset-normalizer (>=3.3.2,<4.0.0)
Requires-Dist: ipython (>=8.34.0,<9.0.0)
Requires-Dist: keyring (>=24.0,<25.0)
Requires-Dist: mariadb (>=1.1.10,<2.0.0)
Requires-Dist: matplotlib (>=3.8.0,<4.0.0)
Requires-Dist: openpyxl (>=3.1.5,<4.0.0)
Requires-Dist: oracledb (>=2.4.1,<3.0.0)
Requires-Dist: pandas (>=2.0.2,<3.0.0)
Requires-Dist: pandasql (>=0.7.3,<0.8.0)
Requires-Dist: psycopg2-binary (>=2.9.10,<3.0.0)
Requires-Dist: pyarrow (>=19.0.0,<20.0.0)
Requires-Dist: pymysql (>=1.1.1,<2.0.0)
Requires-Dist: pyodbc (==5.2.0)
Requires-Dist: pyparsing (>=3.0.9,<4.0.0)
Requires-Dist: pyyaml (>=6.0.1,<7.0.0)
Requires-Dist: seaborn (>=0.13.0,<0.14.0)
Requires-Dist: sqlalchemy (>=2.0.11,<3.0.0)
Requires-Dist: xlrd (>=2.0.1,<3.0.0)
Requires-Dist: xlsxwriter (>=3.1.2,<4.0.0)
Project-URL: Repository, https://github.com/SETT-Centre-Data-and-AI/Kraken
